opentelemetry/instrumentation/faststream/__about__.py
opentelemetry/instrumentation/faststream/__init__.py
opentelemetry/instrumentation/faststream/annotations.py
opentelemetry/instrumentation/faststream/middlewares.py
opentelemetry/instrumentation/faststream/package.py
opentelemetry/instrumentation/faststream/version.py
opentelemetry_instrumentation_faststream-0.1.3.dist-info/METADATA
opentelemetry_instrumentation_faststream-0.1.3.dist-info/WHEEL
opentelemetry_instrumentation_faststream-0.1.3.dist-info/licenses/LICENSE.txt
opentelemetry_instrumentation_faststream-0.1.3.dist-info/RECORD
